.gitignore
.pre-commit-config.yaml
.readthedocs.yaml
CITATION.cff
CODE_OF_CONDUCT.md
LICENSE
MANIFEST.in
README.rst
environment.yaml
pyproject.toml
setup.py
tox.ini
.github/workflows/ci_cron_weekly.yml
.github/workflows/ci_tests.yml
.github/workflows/release.yml
docs/Makefile
docs/changelog.rst
docs/conf.py
docs/developer.rst
docs/image-prior-intuition.png
docs/index.rst
docs/jolideco-illustration.png
docs/jolideco-logo.png
docs/make.bat
docs/patch-priors.png
docs/references.bib
docs/references.rst
docs/_static/css/custom.css
docs/_static/images/jolideco-example.png
docs/user/getting-started.rst
docs/user/index.rst
docs/user/installation.rst
docs/user/overview.rst
examples/README.rst
examples/chandra-e0102-filament.py
examples/fermi-vela-junior.py
examples/first-steps.py
jolideco/__init__.py
jolideco/_astropy_init.py
jolideco/_version.py
jolideco/cli.py
jolideco/conftest.py
jolideco/core.py
jolideco/loss.py
jolideco/version.py
jolideco.egg-info/PKG-INFO
jolideco.egg-info/SOURCES.txt
jolideco.egg-info/dependency_links.txt
jolideco.egg-info/entry_points.txt
jolideco.egg-info/not-zip-safe
jolideco.egg-info/requires.txt
jolideco.egg-info/top_level.txt
jolideco/data/README.rst
jolideco/data/__init__.py
jolideco/data/core.py
jolideco/data/tests/__init__.py
jolideco/data/tests/test_core.py
jolideco/extern/__init__.py
jolideco/models/__init__.py
jolideco/models/core.py
jolideco/models/npred.py
jolideco/models/tests/__init__.py
jolideco/models/tests/test_core.py
jolideco/models/tests/test_npred.py
jolideco/priors/__init__.py
jolideco/priors/core.py
jolideco/priors/lira.py
jolideco/priors/patches/__init__.py
jolideco/priors/patches/core.py
jolideco/priors/patches/gmm.py
jolideco/priors/patches/tests/test_core.py
jolideco/priors/patches/tests/test_gmm.py
jolideco/priors/tests/__init__.py
jolideco/priors/tests/test_core.py
jolideco/priors/tests/test_lira.py
jolideco/tests/__init__.py
jolideco/tests/test_core.py
jolideco/utils/__init__.py
jolideco/utils/misc.py
jolideco/utils/norms.py
jolideco/utils/numpy.py
jolideco/utils/plot.py
jolideco/utils/sympy.py
jolideco/utils/testing.py
jolideco/utils/torch.py
jolideco/utils/io/__init__.py
jolideco/utils/io/asdf.py
jolideco/utils/io/fits.py
