Metadata-Version: 2.1
Name: jolideco
Version: 0.3
Summary: A Python package for Poisson joint likelihood deconvolution
Author-email: Axel Donath <axel.donath@cfa.harvard.edu>
License: BSD 3-Clause
Project-URL: homepage, https://github.com/jolideco/jolideco
Requires-Python: >=3.9
Requires-Dist: torch>=1.13
Requires-Dist: numpy>=1.26
Requires-Dist: astropy>=5.2
Requires-Dist: tqdm
Requires-Dist: click
Requires-Dist: matplotlib
Provides-Extra: all
Requires-Dist: scikit-learn; extra == "all"
Requires-Dist: scikit-image; extra == "all"
Requires-Dist: asdf; extra == "all"
Requires-Dist: asdf-astropy; extra == "all"
Requires-Dist: ruamel.yaml; extra == "all"
Requires-Dist: ruamel.yaml.string; extra == "all"
Requires-Dist: scipy; extra == "all"
Provides-Extra: test
Requires-Dist: pytest; extra == "test"
Requires-Dist: pytest-doctestplus; extra == "test"
Provides-Extra: docs
Requires-Dist: sphinx-book-theme; extra == "docs"
Requires-Dist: sphinx-automodapi; extra == "docs"
Requires-Dist: sphinx-design; extra == "docs"
Requires-Dist: sphinx-gallery; extra == "docs"
Requires-Dist: sphinxcontrib-bibtex; extra == "docs"
Requires-Dist: sympy; extra == "docs"
Requires-Dist: scipy; extra == "docs"
Requires-Dist: sphinxemoji; extra == "docs"
Requires-Dist: gammapy; extra == "docs"
